{
  "attributes": [
    {
      "default": "fragment(\"gen_random_uuid()\")",
      "size": null,
      "type": "uuid",
      "source": "id",
      "references": null,
      "allow_nil?": false,
      "generated?": false,
      "primary_key?": true
    },
    {
      "default": "nil",
      "size": null,
      "type": "bigint",
      "source": "count",
      "references": null,
      "allow_nil?": false,
      "generated?": false,
      "primary_key?": false
    },
    {
      "default": "nil",
      "size": null,
      "type": "text",
      "source": "emoji",
      "references": null,
      "allow_nil?": false,
      "generated?": false,
      "primary_key?": false
    },
    {
      "default": "nil",
      "size": null,
      "type": "bigint",
      "source": "message_id",
      "references": {
        "name": "discord_reactions_message_id_fkey",
        "table": "discord_messages",
        "schema": "public",
        "on_delete": "delete",
        "multitenancy": {
          "global": null,
          "attribute": null,
          "strategy": null
        },
        "primary_key?": true,
        "destination_attribute": "id",
        "deferrable": false,
        "match_type": null,
        "match_with": null,
        "on_update": "update",
        "destination_attribute_default": null,
        "destination_attribute_generated": null
      },
      "allow_nil?": false,
      "generated?": false,
      "primary_key?": false
    }
  ],
  "table": "discord_reactions",
  "hash": "7473ECFC71B86E3F780E42DBA157867B900E78DB1DA04FD50A43CDD9CC45D90F",
  "repo": "Elixir.AshHq.Repo",
  "identities": [
    {
      "name": "unique_message_emoji",
      "keys": [
        "emoji",
        "message_id"
      ],
      "all_tenants?": false,
      "index_name": "discord_reactions_unique_message_emoji_index",
      "base_filter": null
    }
  ],
  "schema": null,
  "multitenancy": {
    "global": null,
    "attribute": null,
    "strategy": null
  },
  "base_filter": null,
  "check_constraints": [],
  "custom_indexes": [],
  "custom_statements": [],
  "has_create_action": true
}